bib_cleaner/__init__.py
bib_cleaner/bib_cleaner.py
bib_cleaner/cli.py
bib_cleaner-0.3.2.dist-info/AUTHORS.rst
bib_cleaner-0.3.2.dist-info/LICENSE
bib_cleaner-0.3.2.dist-info/METADATA
bib_cleaner-0.3.2.dist-info/WHEEL
bib_cleaner-0.3.2.dist-info/entry_points.txt
bib_cleaner-0.3.2.dist-info/top_level.txt
bib_cleaner-0.3.2.dist-info/RECORD
