Metadata-Version: 2.1
Name: bib-cleaner
Version: 0.3.2
Summary: Bib Cleaner removes unnecessary entries from your bib files.
Home-page: https://github.com/sriki18/bib_cleaner
Author: Srikiran Chandrasekaran
Author-email: srikiranc@gmail.com
License: BSD license
Keywords: bib_cleaner
Platform: UNKNOWN
Classifier: Development Status :: 2 - Pre-Alpha
Classifier: Intended Audience :: Developers
Classifier: License :: OSI Approved :: BSD License
Classifier: Natural Language :: English
Classifier: Programming Language :: Python :: 3
Classifier: Programming Language :: Python :: 3.6
Classifier: Programming Language :: Python :: 3.7
Classifier: Programming Language :: Python :: 3.8
Requires-Python: >=3.6
